Report/Parser.py
Report/Recorder.py
Report/__init__.py
Report/__main__.py
nCoV-0.1.7.dist-info/LICENSE
nCoV-0.1.7.dist-info/METADATA
nCoV-0.1.7.dist-info/WHEEL
nCoV-0.1.7.dist-info/entry_points.txt
nCoV-0.1.7.dist-info/top_level.txt
nCoV-0.1.7.dist-info/RECORD
