Metadata-Version: 2.1
Name: nCoV
Version: 0.1.7
Summary: Get instant information about 2019-nCoV
Home-page: https://github.com/EthanGeekFan/nCoV
Author: Yifan Yang
Author-email: yangyifan529@gmail.com
License: UNKNOWN
Platform: UNKNOWN
Classifier: Programming Language :: Python :: 3
Classifier: License :: OSI Approved :: MIT License
Classifier: Operating System :: OS Independent
Classifier: Development Status :: 5 - Production/Stable
Requires-Dist: click
Requires-Dist: beautifulsoup4
Requires-Dist: prettytable
